MANIFEST.in
README
setup.cfg
setup.py
etherdelta/README
etherdelta/__init__.py
etherdelta.egg-info/PKG-INFO
etherdelta.egg-info/SOURCES.txt
etherdelta.egg-info/dependency_links.txt
etherdelta.egg-info/requires.txt
etherdelta.egg-info/top_level.txt
etherdelta/contracts/etherdelta.json
etherdelta/contracts/token.json