Metadata-Version: 1.1
Name: etherdelta
Version: 0.0.22
Summary: Python wrapper for interacting with the EtherDelta API and Smart Contracts.
Home-page: https://github.com/miguelmota/py-etherdelta
Author: Miguel Mota <hello@miguelmota.com>
Author-email: hello@miguelmota.com
License: MIT License
Download-URL: https://github.com/miguelmota/py-etherdelta/archive/master.zip
Keywords: etherdelta
Platform: UNKNOWN
